MANIFEST.in
setup.py
omxremote/__init__.py
omxremote/backend.py
omxremote/dbus_connection.py
omxremote.egg-info/PKG-INFO
omxremote.egg-info/SOURCES.txt
omxremote.egg-info/dependency_links.txt
omxremote.egg-info/not-zip-safe
omxremote.egg-info/requires.txt
omxremote.egg-info/top_level.txt
omxremote/static/index.html
omxremote/static/css/bootstrap-theme.css
omxremote/static/css/bootstrap-theme.css.map
omxremote/static/css/bootstrap-theme.min.css
omxremote/static/css/bootstrap.css
omxremote/static/css/bootstrap.css.map
omxremote/static/css/bootstrap.min.css
omxremote/static/css/sticky-footer.css
omxremote/static/fonts/glyphicons-halflings-regular.eot
omxremote/static/fonts/glyphicons-halflings-regular.svg
omxremote/static/fonts/glyphicons-halflings-regular.ttf
omxremote/static/fonts/glyphicons-halflings-regular.woff
omxremote/static/fonts/glyphicons-halflings-regular.woff2
omxremote/static/js/angular.min.1.3.13.js
omxremote/static/js/app.js
omxremote/static/js/bootstrap.min.js
omxremote/static/js/jquery-1.11.3.min.js
omxremote/static/js/ui-bootstrap-tpls-0.13.0.min.js