Metadata-Version: 1.1
Name: omxremote
Version: 0.1
Summary: remote control for a raspberry pi movie player
Home-page: http://github.com/flurischt/omxremote
Author: Flurin Rindisbacher
Author-email: info@flurischt.ch
License: BSD
Platform: UNKNOWN
Classifier: Development Status :: 4 - Beta
Classifier: Environment :: Web Environment
Classifier: Intended Audience :: End Users/Desktop
Classifier: License :: OSI Approved :: BSD License
Classifier: Operating System :: OS Independent
Classifier: Programming Language :: Python
Classifier: Programming Language :: Python :: 3
Classifier: Topic :: Multimedia :: Video
